pygifconvt_0culty/__init__.py
pygifconvt_0culty/converter.py
pygifconvt_0culty-1.0.0.dist-info/LICENSE
pygifconvt_0culty-1.0.0.dist-info/METADATA
pygifconvt_0culty-1.0.0.dist-info/WHEEL
pygifconvt_0culty-1.0.0.dist-info/top_level.txt
pygifconvt_0culty-1.0.0.dist-info/RECORD
